jayttle_process/ComputerControl.py
jayttle_process/TimeSeriesDataMethod.py
jayttle_process/__init__.py
jayttle_process-1.0.2.dist-info/METADATA
jayttle_process-1.0.2.dist-info/WHEEL
jayttle_process-1.0.2.dist-info/top_level.txt
jayttle_process-1.0.2.dist-info/RECORD
