Metadata-Version: 2.1
Name: jayttle-process
Version: 1.0.2
Summary: en: Data Process;
Home-page: UNKNOWN
Author: Jayttle
Author-email: 294448068@qq.com
License: UNKNOWN
Platform: UNKNOWN
